sphinx_autosummary_autocollect/__init__.py
sphinx_autosummary_autocollect/generate.py
sphinx_autosummary_autocollect-0.1.1.dist-info/LICENSE
sphinx_autosummary_autocollect-0.1.1.dist-info/METADATA
sphinx_autosummary_autocollect-0.1.1.dist-info/WHEEL
sphinx_autosummary_autocollect-0.1.1.dist-info/entry_points.txt
sphinx_autosummary_autocollect-0.1.1.dist-info/RECORD
