Metadata-Version: 2.1
Name: sphinx-autosummary-autocollect
Version: 0.1.1
Summary: Sphinx plugin based on autosummary, that automatically collects symbols if non are provided .
Home-page: https://github.com/helpmefindaname/python-template
License: BSD-2-Clause
Author: Benedikt Fuchs
Author-email: benedikt.fuchs.staw@hotmail.com
Requires-Python: >=3.9,<4.0
Classifier: License :: OSI Approved :: BSD License
Classifier: Programming Language :: Python :: 3
Classifier: Programming Language :: Python :: 3.9
Classifier: Programming Language :: Python :: 3.10
Classifier: Programming Language :: Python :: 3.11
Classifier: Programming Language :: Python :: 3.12
Requires-Dist: sphinx (>=7.2.0)
Project-URL: Repository, https://github.com/helpmefindaname/python-template
